{
  "filename": "curroncol-33-00203.pdf",
  "absolute_path": "/home/softsensor/Documents/Ai_project/cha/curroncol-33-00203.pdf",
  "num_pages": 10,
  "metadata": {
    "/Keywords": "staging investigations; breast cancer; neoadjuvant chemotherapy; locallyadvanced; systemic staging",
    "/Creator": "LaTeX with hyperref",
    "/ModDate": "D:20260401104106+02'00'",
    "/Trapped": "/False",
    "/CreationDate": "D:20260401163227+08'00'",
    "/Producer": "pdfTeX-1.40.25; modified using OpenPDF 1.4.2",
    "/Subject": "Background: Patients with breast cancer planned for neoadjuvant chemotherapy (NAC) represent a diverse population including high-risk early breast cancer (EBC) and locally advanced breast cancer (LABC). Staging investigations are routinely performed, but the clinical utility is unclear. Methods: Using a provincial cancer registry, we identified breast cancer patients referred for NAC between 2020 and 2022. Patients with staging investigations were stratified into EBC (anatomic clinical stage I–II) and LABC (stage III). Rates of metastatic (M1) disease and associated factors were assessed. Results: Among 529 EBC patients, 515 (97.4%) underwent staging. The M1 disease rate was 5.4%. The M1 rate for cT1-2N0 was 1.1%, and for cT1-2N1 it was 7.9%. In multivariable analysis, cT1N1 (OR 5.31; 95% CI 1.05–27.0; p = 0.044) and cT2N1 (OR 4.59; 95% CI 1.02–20.67; p = 0.047) were associated with M1 disease in EBC. All 320 LABC patients underwent staging. The M1 disease rate was 22.8%, significantly higher than in EBC (p < 0.001). A higher cT/N stage correlated with M1 disease in LABC, although most subgroups demonstrated rates of 10%. Conclusions: These findings support a risk-adapted approach to pre-treatment staging in patients planned for NAC, omitting staging in asymptomatic cT1–2N0 disease, considering it for node-positive EBC, and performing it routinely in LABC.",
    "/PTEX.Fullbanner": "This is pdfTeX, Version 3.141592653-2.6-1.40.25 (TeX Live 2023) kpathsea version 6.3.5",
    "/Author": "Kadhim Taqi, Camelia Ursu, Susan Isherwood, Rabia Raheel, Julia Downey, Jeffrey Q. Cao, Sasha Lupichuk, Omar Khan, Nancy Nixon, May Lynn Quan and Alison Laws",
    "/Title": "The Yield of Staging Investigations in Patients with Breast Cancer Planned for Neoadjuvant Chemotherapy"
  },
  "pages": [
    "Received: 11 February 2026\nRevised: 25 March 2026\nAccepted: 31 March 2026\nPublished: 1 April 2026\nCopyright: © 2026 by the authors.\nLicensee MDPI, Basel, Switzerland.\nThis article is an open access article\ndistributed under the terms and\nconditions of the Creative Commons\nAttribution (CC BY) license.\nArticle\nThe Yield of Staging Investigations in Patients with Breast\nCancer Planned for Neoadjuvant Chemotherapy\nKadhim Taqi1,2,*\n, Camelia Ursu3, Susan Isherwood4, Rabia Raheel4, Julia Downey5, Jeffrey Q. Cao6,7,\nSasha Lupichuk8\n, Omar Khan8\n, Nancy Nixon8, May Lynn Quan1,5,7and Alison Laws1,7,*\n1Division of Surgical Oncology, Department of Surgery, University of Calgary, Calgary, AB T2N 1N4, Canada\n2Division of Surgical Oncology, Department of Surgery, Sultan Qaboos Comprehensive Cancer Care and\nResearch Center, University Medical City, Muscat 123, Oman\n3Cumming School of Medicine, University of Calgary, Calgary, AB T2N 1N4, Canada\n4Department of Surgery, University of Calgary, Calgary, AB T2N 1N4, Canada\n5Department of Community Health Sciences, University of Calgary, Calgary, AB T2N 1N4, Canada\n6Division of Radiation Oncology, Arthur J.E. Child Comprehensive Cancer Centre,\nCalgary, AB T2N 1N4, Canada\n7Department of Oncology, University of Calgary, Calgary, AB T2N 1N4, Canada\n8Division of Medical Oncology, Department of Oncology, University of Calgary, Calgary, AB T2N 1N4, Canada\n*Correspondence: kadhim.taqi@ucalgary.ca (K.T.); alison.laws@albertahealthservices.ca (A.L.)\nSimple Summary\nRadiological imaging is commonly used in patients with breast cancer to assess disease\nstage before starting chemotherapy, but its benefit varies by stage. Using population-\nwide data, we studied how often these tests detected cancer that had already spread in\npatients planned for chemotherapy before surgery. We found that cancer spread was very\nuncommon in patients with small tumors and no lymph node involvement, even when\nchemotherapy was planned, suggesting that routine staging scans can be safely avoided\nin this group. In contrast, patients with larger tumors or lymph node involvement had\na higher likelihood of cancer spread. These results support more selective use of staging\ntests, which could reduce unnecessary scans, costs, patient anxiety, and treatment delays,\nwhile helping refine future guidelines and policy decisions.\nAbstract\nBackground: Patients with breast cancer planned for neoadjuvant chemotherapy (NAC)\nrepresent a diverse population including high-risk early breast cancer (EBC) and locally\nadvanced breast cancer (LABC). Staging investigations are routinely performed, but the\nclinical utility is unclear. Methods: Using a provincial cancer registry, we identified\nbreast cancer patients referred for NAC between 2020 and 2022. Patients with staging\ninvestigations were stratified into EBC (anatomic clinical stage I–II) and LABC (stage III).\nRates of metastatic (M1) disease and associated factors were assessed. Results: Among\n529 EBC patients, 515 (97.4%) underwent staging. The M1 disease rate was 5.4%. The M1\nrate for cT1-2N0 was 1.1%, and for cT1-2N1 it was 7.9%. In multivariable analysis, cT1N1\n(OR 5.31; 95% CI 1.05–27.0; p= 0.044) and cT2N1 (OR 4.59; 95% CI 1.02–20.67; p= 0.047)\nwere associated with M1 disease in EBC. All 320 LABC patients underwent staging. The\nM1 disease rate was 22.8%, significantly higher than in EBC ( p< 0.001). A higher cT/N\nstage correlated with M1 disease in LABC, although most subgroups demonstrated rates\nof≥10%. Conclusions: These findings support a risk-adapted approach to pre-treatment\nstaging in patients planned for NAC, omitting staging in asymptomatic cT1–2N0 disease,\nconsidering it for node-positive EBC, and performing it routinely in LABC.\nCurr. Oncol. 2026 ,33, 203 https://doi.org/10.3390/curroncol33040203",
    "Curr. Oncol. 2026 ,33, 203 2 of 10\nKeywords: staging investigations; breast cancer; neoadjuvant chemotherapy; locally\nadvanced; systemic staging\n1. Introduction\nStaging investigations alter the management of patients newly diagnosed with breast\ncancer when distant metastatic disease is identified. In patients with locoregionally ad-\nvanced breast cancer (LABC), systemic staging is recommended due to the relatively high\nlikelihood of detecting distant metastases [ 1–3]. Conversely, the diagnostic yield of staging\nis much lower for early breast cancer (EBC), and thus its use is more debated, with current\nguidelines varying in their recommendations. The National Comprehensive Cancer Net-\nwork (NCCN), American Society of Clinical Oncology (ASCO) and Cancer Care Ontario\ndiscourage routine staging for asymptomatic patients with stage I or II disease [ 1,4,5]. In\ncontrast, the European Society for Medical Oncology (ESMO) supports the use of staging\nfor patients with node-positive disease, tumors larger than 5 cm (T3), or aggressive tumor\nbiology (3), while the American College of Radiology (ACR) recommends staging for\npatients with stage IIB or higher disease [6].\nPatients referred for neoadjuvant chemotherapy (NAC) represent a distinct subgroup\nencompassing both early and locally advanced disease. These patients often present with\nhigher-risk features that render them eligible for NAC such as node positivity or more\naggressive biologic subtypes (even when presenting with a lower anatomic clinical stage).\nThe diagnostic yield and clinical utility of staging investigations in this population is not\nwell-characterized. Multiple studies have shown high rates of staging in patients with EBC,\nespecially before NAC initiation [ 7–9]. Overuse of staging investigations is costly [ 7,10] and\nmay expose patients to harms such as unnecessary radiation, invasive follow-up procedures,\nand anxiety over false-positive findings [ 11]. Further, staging workups can delay the timely\ninitiation of therapy, potentially impacting treatment outcomes [ 12]. Nevertheless, accurate\nassessment of disease extent remains crucial for prognostication and to guide treatment\nstrategies, including avoidance of chemotherapy toxicity for some patients when metastatic\ndisease is confirmed.\nAcross the six tertiary and regional cancer centers in the province of Alberta, Canada,\ndistant staging investigations are performed routinely for patients with breast cancer\nplanned for NAC. The objective of this study was to evaluate the rate of de novo metastatic\n(M1) disease detected in staging investigations among patients referred for NAC, stratified\nby EBC and LABC, and to identify factors associated with M1 disease.\n2. Materials and Methods\nInstitutional review board approval was obtained from the Health Research Ethics\nBoard of Alberta–Cancer Committee (HREBA-CC), and a waiver of consent was granted\ngiven the minimal-risk nature of the study. All patients with breast cancer referred to\nmedical oncology for consideration of NAC between 2020 and 2022 were identified from the\nAlberta Cancer Registry, which captures all new cancers in the province of approximately\nfive million individuals. Patients who did not undergo any distant staging investigations\nwere excluded. Two cohorts were generated based on the clinical T/N stage (cT/cN) at\npresentation according to the American Joint Committee on Cancer (AJCC) 8th edition\nanatomic staging system. The EBC cohort was defined as stage I-II (cT1-2 N0-1 or cT3N0)\nand the LABC cohort as stage III (cT3N1, any cT4, and any cN2-3).\nThe primary outcome of interest was final metastatic status after staging (M0 vs. M1),\nobtained from the Alberta Cancer Registry and confirmed in the medical record. Details of\nhttps://doi.org/10.3390/curroncol33040203",
    "Curr. Oncol. 2026 ,33, 203 3 of 10\nthe staging workup were obtained from medical chart review. Each distant staging investi-\ngation was documented, including computed tomography (CT) of the chest and abdomen\nwith or without pelvis (CA ±P), bone scan, brain imaging (CT or Magnetic Resonant\nImaging (MRI)) and positron emission tomography (PET). Staging results according to the\nreporting radiologist’s interpretation were categorized as negative (any findings considered\nlikely benign), indeterminate (findings could not be confidently classified as benign or\nmalignant) or suspicious (findings were concerning for malignancy and considered likely\nmetastatic). Further workup was defined as additional imaging tests or biopsies prompted\nby findings on the baseline staging scans.\nRemaining demographic, disease and treatment characteristics were obtained from\nmedical chart review. Histological type, grade, estrogen receptor (ER), progesterone recep-\ntor (PR), and human epidermal growth factor receptor-2 (HER2) status were obtained from\nthe pre-treatment core biopsy. Hormone receptor positivity (HR+) and HER2 positivity\n(HER2+) were defined according to the American Society of Clinical Oncology and the\nCollege of American Pathologists (ASCO/CAP) guidelines [ 13] and were used to construct\nbiologic subtype categories of HR+/HER2 −, HER2+ and triple-negative (TN).\nStatistical Analysis\nThe EBC and LABC cohorts were analyzed separately. Descriptive statistics were used\nto summarize demographic and disease characteristics, with continuous variables reported\nas medians with interquartile ranges (IQRs) and categorical variables as frequencies and\nproportions. Time from pathologic diagnosis (biopsy date) to NAC initiation was compared\nby staging result using Mann–Whitney U tests. Associations between clinical factors (age,\ncT and cN, histologic type, grade, and biologic subtype) and M1 status were evaluated\nusing univariable logistic regression. Factors with statistically significant associations were\nincluded in multivariable logistic regression models. For the EBC cohort, the multivariable\nmodel included cT/N category, grade and biologic subtype (histologic type was excluded\ndue to a small sample size of lobular cancers). For the LABC cohort, samples sizes were\nsmall for individual cT/N categories. As such, two models were generated, one including\ncT and cN as separate variables and one using AJCC subgroups of stage III (A vs. B vs.\nC), along with age and grade. For both cohorts, we reported absolute rates of M1 disease\nfor pre-planned subgroups of cT/N category and biologic subtype, reflecting groups for\nwhich staging investigations have been recommended in some guidelines. All analyses\nwere performed using StataIC version 16.1 (StataCorp LLC, College Station, TX, USA). A\np-value of <0.05 was considered statistically significant.\n3. Results\n3.1. Early Breast Cancer Cohort (Stage IA-IIB)\nAmong 529 eligible patients with EBC, 14 patients had no staging investigations and\nwere excluded. The remaining 515 (97.4%) underwent CT CA +/ −P and/or bone scan\nand were included for analysis. Most patients ( n= 469, 91.1%) had guideline-concordant\nstaging with both CT CA ±P and bone scan. Additional brain imaging was performed\nfor 48 patients (9.3%) and an additional PET scan for 4 patients (0.8%). Detailed staging\nresults are shown in Figure 1. Overall, M1 disease was identified in 28/515 patients (5.4%;\n95% CI, 3.8–7.7%). Sites of distant metastases were as follows: lung ( n= 14, 50.0%), bone\n(n= 12, 42.9%), liver ( n= 11, 39.3%), brain ( n= 1, 3.6%), and other ( n= 9, 32.2%). Among\nM0 patients, those who required additional workup ( n= 114, 22.1%) after baseline staging\nscans experienced a median delay of five days to NAC initiation (43 vs. 38 days; p= 0.03).\nhttps://doi.org/10.3390/curroncol33040203",
    "Curr. Oncol. 2026 ,33, 203 4 of 10\nFigure 1. Results of staging investigations in patients with early and locoregionally advanced breast\ncancer referred for neoadjuvant chemotherapy.\nClinical characteristics stratified by M0 versus M1 disease are presented in Table 1.\nClinical T/N stage, histology, grade and biologic subtype were all significantly associated\nwith M1 status (all p< 0.05) in univariable analyses. In multivariable analysis, only the\ncT1N1 (OR 5.31; 95% CI 1.05–27.0; p= 0.044) and cT2N1 (OR 4.59; 95% CI 1.02–20.67;\np= 0.047 ) stage remained significantly associated with higher odds of M1 disease (Table 2).\nWhile not statistically significant, TN or HER2+ subtypes and grade 3 tumors showed\nlower odds of M1 disease. Rates of M1 disease in pre-specified subgroups of cT/N category\nand biologic subtype are presented in Table 3. Most notably, the M1 rate was 1.1% (2/174)\nfor cT1-2N0, 5.4% (2/37) for cT3N0 and 7.9% (24/302) for cT1-2N1.\nTable 1. Baseline characteristics for early breast cancer (stage I–II) patients with M0 vs. M1 disease.\nVariable M0 ( n= 487) M1 ( n= 28) p-Value\nMedian age in years (IQR) 50 (42–60) 53 (47–62) 0.17\ncT/N stage\n0.04T1N0 36 (7.4%) 0 (0%)\nT2N0 138 (28.3%) 2 (7.1%)\nT1N1 71 (14.6%) 7 (25.0%)\nT2N1 207 (42.5%) 17 (60.7%)\nT3N0 35 (7.2%) 2 (7.1%)\nHistology\n0.02 Ductal 473 (97.1%) 25 (89.3%)\nLobular 14 (2.9%) 3 (10.7%)\nGrade\n0.04 1–2 158 (32.4%) 15 (53.6%)\n3 326 (66.9%) 13 (46.4%)\nER Status\n0.002 Positive 238 (48.9%) 22 (78.6%)\nNegative 249 (51.1%) 6 (21.4%)\nPR Status\n0.015 Positive 153 (31.4%) 15 (53.6%)\nNegative 334 (68.6%) 13 (46.4%)\nhttps://doi.org/10.3390/curroncol33040203",
    "Curr. Oncol. 2026 ,33, 203 5 of 10\nTable 1. Cont.\nVariable M0 ( n= 487) M1 ( n= 28) p-Value\nHER2 Status\n0.33 Positive 184 (37.8%) 8 (28.6%)\nNegative 303 (62.2%) 20 (71.4%)\nBiologic subtype\n0.005HR+/HER2 − 126 (25.9%) 15 (53.6%)\nTN 177 (36.3%) 5 (17.9%)\nHER2+ 184 (37.8%) 8 (28.5%)\nIQR: interquartile range. cT: clinical tumor stage. cN: clinical nodal stage. HR: hormone receptor. TN: triple-\nnegative. HER2: human epidermal growth factor receptor-2.\nTable 2. Multivariable analysis evaluating factors associated with M1 status in the early breast cancer\n(stage I–II) cohort.\nVariableUnadjusted\nOdds RatioAdjusted\nOdds RatioAdjusted 95%\nConfidence\nIntervalAdjusted\np-Value\ncT/N stage\nT1N0 No events No events - -\nT2N0 Reference Reference\nT3N0 3.94 2.35 0.30–18.28 0.414\nT1N1 6.80 5.31 1.05–26.99 0.044\nT2N1 5.67 4.59 1.02–20.67 0.047\nGrade\n1–2 Reference Reference\n3 0.40 0.48 0.22–1.08 0.076\nBiologic subtype\nHR+/HER2 − Reference Reference\nTN 0.24 0.43 0.14–1.27 0.125\nHER2+ 0.37 0.50 0.20–1.24 0.134\ncT stage: clinical tumor stage. cN stage: clinical nodal stage. HR: hormone receptor. TN: triple-negative. HER2:\nhuman epidermal growth factor receptor-2.\nTable 3. Absolute rates of M1 disease by cT/N stage and biologic subtype.\nOverall AJCC Stage cT/N All Biologic Subtypes HR+/HER2 − TN HER2+\nIA T1N0 0/36 (0%) -- -- --\nIIAT2N0 2/138 (1.4%) 0/17 (0%) 0/69 (0%) 2/52 (3.7%)\nT1N1 7/78 (9.0%) 5/28 (17.9%) 1/25 (4.0%) 1/25 (4.0%)\nIIBT3N0 2/37 (5.4%) 2/19 (10.5%) 0/12 (0%) 0/6 (0%)\nT2N1 17/224 (7.6%) 8/75 (10.7%) 4/60 (6.7%) 5/89 (5.6%)\nIIIAT1-2N2 2/43 (4.7%) 1/17 (5.9%) 0/10 (0%) 1/16 (6.3%)\nT3N1 9/77 (11.7%) 5/36 (13.9%) 1/13 (7.7%) 3/28 (10.7%)\nT3N2 1/10 (10.0%) * * *\nIIIBT4N0 4/17 (23.5%) * * *\nT4N1 23/80 (28.8%) 13/42 (31.0%) 1/12 (8.3%) 9/26 (34.6%)\nT4N2 7/19 (36.8%) * * *\nIIICT1-2N3 9/24 (37.5%) 4/13 (30.8%) 1/4 (25.0%) 4/7 (57.1%)\nT3N3 4/16 (25.0%) * * *\nT4N3 14/33 (42.4%) 3/7 (42.9%) 7/12 (58.3%) 4/14 (28.6%)\ncT stage: clinical tumor stage. cN stage: clinical nodal stage. HR: hormone receptor. TN: triple-negative.\nHER2: human epidermal growth factor receptor-2. * Omitted due to small sample size (<20 patients in total).\nhttps://doi.org/10.3390/curroncol33040203",
    "Curr. Oncol. 2026 ,33, 203 6 of 10\n3.2. Locally Advanced Breast Cancer Cohort (Stage III)\nAmong 320 eligible patients with LABC, all (100%) underwent CT CA +/ −P and/or\nbone scan and were included for analysis. Most patients ( n= 293; 91.5%) received guideline-\nconcordant staging with both CT CA ±P and a bone scan. Additional brain imaging was\nperformed in 40 patients (12.5%) and an additional PET scan in 7 patients (2.2%). Detailed\nstaging results are shown in Figure 1. Overall, M1 disease was identified in 73/320 patients\n(22.8%; 95% CI, 18.6–27.7%), a significantly higher rate than the EBC cohort ( p< 0.001).\nSites of distant metastases were as follows: bone ( n= 41, 56.2%), lung ( n= 39, 53.4%), liver\n(n= 29, 39.7%), brain ( n= 3, 4.1%) and other ( n= 25, 34.2%). Among M0 patients, those\nwho required additional workup after baseline staging scans did not experience any delay\nto NAC initiation (median 36 days for both, p= 0.54).\nClinical characteristics stratified by M0 versus M1 disease are shown in Table 4. Age,\ncT and cN categories as well as overall AJCC stage, and grade were significantly associated\nwith M1 disease (all p< 0.05) in univariable analyses. In multivariable analysis, cT4 and\ncN3 disease remained significantly associated with higher odds of M1 disease, whereas\nstage IIIA disease (vs. IIIB or IIIC) and grade 3 were associated with significantly lower\nodds of M1 (all p< 0.05, Supplementary Tables S1 and S2). Notably, all cT, cN, and grade\nsubgroups for the LABC cohort had absolute M1 rates ≥10%. The absolute rate of M1\ndisease for stage IIIA was 9.2% (12/130); rates for each T/N category are shown in Table 3.\nTable 4. Baseline characteristics for locally advanced patients (stage III) with M0 vs. M1 disease.\nVariable M0 ( n= 247) M1 ( n= 73) p-Value\nMedian age in years (IQR) 49 (41–62) 57 (44–67) 0.01\ncT\n<0.0011–2 57 (23.0%) 11 (15.0%)\n3 89 (36.0%) 14 (19.2%)\n4a-c 39 (15.8%) 30 (41.1%)\n4d 62 (25.1%) 18 (25.7%)\ncN\n0.0090 13 (5.3%) 4 (5.5%)\n1 125 (50.6%) 32 (43.8%)\n2 62 (25.1%) 10 (13.7%)\n3 47 (19.0%) 27 (37.0%)\nStage\n<0.001IIIA (T3N1 and T0-3 N2) 118 (47.8%) 12 (16.4%)\nIIIB (T4 N0-2) 82 (33.2%) 34 (46.6%)\nIIIC (T any N3) 47 (19.0%) 27 (37.0%)\nHistology\n0.74 Ductal 240 (97.2%) 72 (98.6%)\nLobular 6 (2.4%) 1 (1.4%)\nGrade\n0.003 1–2 68 (27.5%) 34 (46.6%)\n3 179 (72.5%) 39 (53.4%)\nER Status\n0.23 Positive 150 (60.7%) 50 (68.5%)\nNegative 97 (39.3%) 23 (31.5%)\nPR Status\n0.33 Positive 106 (42.9%) 36 (49.3%)\nNegative 141 (57.1%) 37 (50.7%)\nHER2 Status\n0.91 Positive 83 (33.6%) 24 (32.9%)\nNegative 164 (66.4%) 49 (67.1%)\nhttps://doi.org/10.3390/curroncol33040203",
    "Curr. Oncol. 2026 ,33, 203 7 of 10\nTable 4. Cont.\nVariable M0 ( n= 247) M1 ( n= 73) p-Value\nBiologic subtype\n0.76HR+/HER2 − 108 (43.7%) 35 (48.0%)\nTN 56 (22.7%) 14 (19.2%)\nHER2+ 83 (33.6%) 24 (32.9%)\nIQR: interquartile range. cT: clinical tumor stage. cN: clinical nodal stage. HR: hormone receptor. TN: triple-\nnegative. HER2: human epidermal growth factor receptor-2.\n4. Discussion\nThis study uniquely uses a large population-based cohort of breast cancer patients\nreferred for NAC with unselected use of staging investigations, allowing for an accurate\nand generalizable assessment of the diagnostic yield of staging in this population. We found\na low rate of M1 disease among patients with cT1–T2N0 disease (1% overall), supporting\nthe omission of routine staging in this population even when NAC is planned, which is\nconsistent with current guidelines for all-comers with early breast cancer [ 3–5]. In contrast,\nthe incidence of M1 disease was higher for EBC patients with cT3N0 (5%) and N1 (8–9%)\ndisease, suggesting that staging may be justified in these subgroups. Notably, a trend\ntoward higher M1 rates was also observed among patients with ER+/HER2 −subtype\nand grade 1–2 tumors. While these did not reach statistical significance in multivariable\nanalysis, the low event rate may have limited power. Nonetheless, our findings do not\nclearly support preferential use of staging in aggressive subtypes (e.g., TN and HER2+)\neven at a lower clinical stage of disease, as some guidelines have suggested, though this\nobservation should be interpreted with caution. In contrast, patients with LABC exhibited\na significantly higher burden of metastatic disease, with even the lowest-risk subgroups\ndemonstrating M1 rates of ≥9–10%, reinforcing guideline recommendations for routine\nstaging in this population.\nMost studies evaluating the diagnostic yield of staging investigations in breast can-\ncer included all-comers and were stratified by stage. In such studies, the overall rate\nof M1 disease is low (0–6%) for EBC populations [ 11,13,14] but significant for LABC\n(18–36%) [8,10,15–17] . The likelihood of M1 disease has also been generally consistent\nacross tumor subtypes [ 13,14]. Cohorts of high-risk subgroups such as patients referred\nfor NAC are more limited. A retrospective review from Memorial Sloan Kettering Cancer\nCentre [ 7] included 303 NAC patients with stage I-II disease, of whom 85% had staging\ninvestigations, mostly with PET/CT. The M1 rate detected by staging was 4.9%, almost\nall (n= 14/15) in patients with cN1 disease. They concluded that pre-NAC staging is not\nnecessary for patients with EBC. A study from the United Kingdom evaluated 163 patients\nreferred for NAC where staging was routine. The overall rate of M1 disease was 9.3%,\nbut in the cohort with T1-3N0, the rate was only 1.6% [ 9]. Our findings are aligned with\nthese prior studies, but our larger sample size allowed for further stratification by stage\nand biologic subtype to develop recommendations more tailored to individual tumor\ncharacteristics.\nIn our cohort, staging investigations resulted in small delays to treatment (median\n5 days) for patients who required additional workup after baseline scans. While time-to-\ntreatment benchmarks are lacking for NAC patients specifically, delays of ≥4–8 weeks\nfrom breast cancer diagnosis to treatment are associated with worse outcomes in those\nundergoing surgery first [ 18–20]. As such, the differences in time to treatment observed in\nour study are likely clinically insignificant. Other studies have found delays of 6–14 days for\npatients who undergo staging [ 21], so this issue warrants consideration in the local context.\nhttps://doi.org/10.3390/curroncol33040203",
    "Curr. Oncol. 2026 ,33, 203 8 of 10\nSeveral limitations of this study should be acknowledged. Despite the large overall\nsample of 835 patients, stratification by clinical T/N stage and biologic subtype resulted\nin small subgroup sizes, limiting the precision of some estimates. Similarly, multivariable\nanalyses—particularly in the EBC cohort—may have been underpowered given the rel-\natively low event rate. Given the retrospective nature of this study, there is a possibility\nof selection bias in staging use and potential for heterogeneity in the type of modality\nchosen, both of which could influence diagnostic yield. However, exclusions due to non-\nperformance of staging were very minimal ( n= 14 patients, 1.6%) and type of staging\nwas quite homogenous, with 91% of patients in both EBC and LABC cohorts undergoing\nguideline-concordant CT CA +/ −P and bone scan. Collectively, this supports the minimal\nrisk of these issues. PET scan was infrequently used in this population, limiting the gener-\nalizability of our findings to centers where this modality is routinely incorporated. PET has\nbeen shown to increase the detection of M1 disease and is being increasingly incorporated\ninto clinical practice guidelines, primarily for LABC [ 1,4,22]. In addition, clinical staging\nwas used for group classification, which may be subject to misclassification, particularly\nwith respect to nodal assessment. However, this reflects the reality of available information\nbefore NAC is initiated. Finally, with any retrospective medical chart review, there is a\nrisk of variable misclassification, though variables included in this study were generally\nclearly documented.\n5. Conclusions\nBased on our findings, we advocate for the omission of routine staging investigations\nfor asymptomatic patients with cT1-2N0 disease planned for NAC, in keeping with current\nguideline recommendations. EBC patients with cT3N0 or N1 disease may be considered\nfor staging, and staging should be routine for those with LABC. Staging guidelines in our\nprovince are currently under review and will be informed by this study, and our results are\nwidely generalizable to other jurisdictions.\nSupplementary Materials: The following supporting information can be downloaded at:\nhttps://www.mdpi.com/article/10.3390/curroncol33040203/s1, Table S1: Multivariable analysis #1\nevaluating factors associated with M1 status in the locally advanced (stage III) cohort, including age,\ncT, cN and grade; Table S2: Multivariable analysis #2 evaluating factors associated with M1 status in\nthe locally advanced (stage III) cohort, including age, overall AJCC stage and grade.\nAuthor Contributions: Conceptualization, K.T., A.L. and M.L.Q.; methodology, S.I. and A.L.; valida-\ntion, K.T., M.L.Q. and A.L.; formal analysis, A.L.; investigation, K.T. and C.U.; resources, S.I.; data\ncuration, C.U., R.R. and J.D.; writing—original draft preparation, K.T.; writing—review and editing,\nJ.Q.C., S.L., O.K., N.N., M.L.Q. and A.L.; visualization, A.L.; supervision, A.L.; project administration,\nS.I. All authors have read and agreed to the published version of the manuscript.\nFunding: This research received no external funding.\nInstitutional Review Board Statement: The study was conducted in accordance with the Declaration\nof Helsinki and approved by the Institutional Review Board of the Health Research Ethics Board of\nAlberta (HREBA)–Cancer Committee (CC). (Approval code: HREBA.CC-24-0235; Approval Date: 8\nAugust 2024).\nInformed Consent Statement: Patient consent was waived by the ethical board (Health Research\nEthics Board of Alberta–Cancer Committee) given the minimal-risk nature of the study.\nData Availability Statement: The datasets generated during and/or analyzed during the current\nstudy are not publicly available due to patient privacy but are available from the corresponding\nauthor on reasonable request.\nConflicts of Interest: The authors declare no conflicts of interest.\nhttps://doi.org/10.3390/curroncol33040203",
    "Curr. Oncol. 2026 ,33, 203 9 of 10\nAbbreviations\nThe following abbreviations are used in this manuscript:\nLABC Locally advanced breast cancer\nEBC Early breast cancer\nNCCN National Comprehensive Cancer Network\nASCO American Society of Clinical Oncology\nESMO European Society of Medical Oncology\nACR American College of Radiology\nNAC Neoadjuvant chemotherapy\nM1 De novo metastatic\nAJCC American Joint Committee on Cancer\nCT Computed tomography\nMRI Magnetic resonant imaging\nPET Positron emission tomography\nCA±P Chest and abdomen with or without pelvis\nER Estrogen receptor\nPR Progesterone receptor\nHER2 Epidermal growth factor receptor-2\nHR+ Hormone receptor positivity\nHER2+ HER2 receptor positivity\nCAP College of American Pathologists\nIQRs Interquartile ranges\nTN Triple-negative\nOR Odds ratio\nReferences\n1. Gradishar, W.; Moran, M.; Abraham, J.; Abramson, V .; Aft, R.; Agnese, D.; Allison, K.; Anderson, B.; Bailey,\nJ.; Burstein, H.; et al. National Comprehensive Cancer Network. In NCCN Clinical Practice Guidelines in Oncol-\nogy: Breast Cancer ; National Comprehensive Cancer Network: Fort Washington, PA, USA, 2025. Available online:\nhttps://www.nccn.org/professionals/physician_gls/pdf/breast.pdf (accessed on 20 October 2025).\n2. American Society of Clinical Oncology; American Board of Internal Medicine. Choosing Wisely: Cancer Tests and Treatments.\nPublished 2012. Available online: http://www.choosingwisely.org/patient-resources/cancer-tests-and-treatments (accessed on\n20 October 2025).\n3. Loibl, S.; André, F.; Bachelot, T.; Barrios, C.; Burstein, H.; Cadoso, M.; Carey, L.; Dawood, S.; Del Mastro, L.; Denkert, C.; et al.\nEarly breast cancer: ESMO Clinical Practice Guideline for diagnosis, treatment and follow-up. Ann. Oncol. 2024 ,35, 159–182.\n[CrossRef] [PubMed]\n4. Arnaout, A.; Varela, N.P .; Allarakhia, M.; Grimard, L.; Hey, A.; Lau, J.; Thain, L.; Eisen, A. Baseline staging imaging for distant\nmetastasis in women with stage I, II, and III breast cancer. Curr. Oncol. 2020 ,27, e123–e145. [CrossRef] [PubMed]\n5. American Society of Clinical Oncology. Choosing Wisely. ASCO. Available online: https://www.asco.org/news-\ninitiatives/current-initiatives/cancer-care-initiatives/value-cancer-care/choosing-wisely (accessed on 2 November 2025).\n6. Expert Panel on Breast Imaging; McDonald, E.S.; Scheel, J.R.; Lewin, A.A.; Weinstein, S.; Dodelzon, K.; Dogan, B.; Fitzpatrick, A.;\nKuzmiak, C.; Newell, M.; et al. ACR Appropriateness Criteria®Imaging of Invasive Breast Cancer. J. Am. Coll. Radiol. 2024 ,21,\nS168–S202. [CrossRef] [PubMed]\n7. Srour, M.K.; Lee, M.; Walcott-Sapp, S.; Luu, M.; Chung, A.; Giuliano, A.; Amersi, F. Overuse of preoperative staging of patients\nundergoing neoadjuvant chemotherapy for breast cancer. Ann. Surg. Oncol. 2019 ,26, 3289–3294. [CrossRef] [PubMed]\n8. Roszkowski, N.; Lam, S.S.; Copson, E.; Cutress, R.I.; Oeppen, R. Expanded criteria for pretreatment staging CT in breast cancer.\nBJS Open 2021 ,5, zraa006. [CrossRef] [PubMed]\n9. Broadbent, R.; Ralston, S.; Lauder, J.; Howell, S. Outcome of CT staging prior to neoadjuvant chemotherapy in patients with early\nbreast cancer. Breast J. 2020 ,26, 2415–2419. [CrossRef] [PubMed]\n10. Srour, M.K.; Lee, M.; Walcott-Sapp, S.; Luu, M.; Chung, A.; Giuliano, A.; Amersi, F. Incidental radiologic findings in breast cancer\npatients who undergo staging prior to neoadjuvant chemotherapy. Breast J. 2021 ,27, 345–351. [CrossRef]\n11. Kamel, D.; Youssef, V .; Hopman, W.M.; Mates, M. Staging investigations in asymptomatic early breast cancer patients at the\nCancer Centre of Southeastern Ontario. Curr. Oncol. 2021 ,28, 2190–2198. [CrossRef]\nhttps://doi.org/10.3390/curroncol33040203",
    "Curr. Oncol. 2026 ,33, 203 10 of 10\n12. Lohrisch, C.; Paltiel, C.; Gelmon, K.; Speers, C.; Taylor, S.; Barnett, J.; Olivotto, I. Impact on survival of time from definitive surgery\nto initiation of adjuvant chemotherapy for early-stage breast cancer. J. Clin. Oncol. 2006 ,24, 4888–4894. [CrossRef] [PubMed]\n13. Allison, K.H.; Hammond, M.E.H.; Dowsett, M.; McKernin, S.; Carey, L.; Fitzgibbons, P .; Hayes, D.; Lakhani, S.; Chavez-MacGregor,\nM.; Perlmutter, J.; et al. Estrogen and progesterone receptor testing in breast cancer: ASCO/CAP guideline update. J. Clin. Oncol.\n2020 ,38, 1346–1366. [CrossRef] [PubMed]\n14. Bychkovsky, B.L.; Guo, H.; Sutton, J.; Spring, L.; Faig, J.; Dagogo-Jack, I.; Battelli, C.; Houlihan, M.J.; Yeh, T.C.; Come, S.E.; et al.\nUse and Yield of Baseline Imaging and Laboratory Testing in Stage II Breast Cancer. Oncologist 2016 ,21, 1495–1501. [CrossRef]\n[PubMed]\n15. Barrett, T.; Bowden, D.J.; Greenberg, D.C.; Brown, C.; Wishart, G.; Britton, P . Radiological staging in breast cancer: Which\nasymptomatic patients to image and how. Br. J. Cancer 2009 ,101, 1522–1528. [CrossRef] [PubMed]\n16. Alkazaz, A.A.; Ali, N.F.; Salman, A.Z.; Almahari, S.; Altaei, T.; Albati, W.; Habib, H.; Alsadoon, A.; Almawlani, N.; Alkhabbaz, F.;\net al. Need for staging investigations in newly diagnosed breast cancer: Establishing local guidelines for radiological staging in\nBahrain. Eur. J. Breast Health 2024 ,20, 136–140. [CrossRef] [PubMed]\n17. Ali, B.; Mubarik, F.; Zahid, N.; Sattar, A.K. Clinicopathologic features predictive of distant metastasis in patients diagnosed with\ninvasive breast cancer. JCO Glob. Oncol. 2020 ,6, 1346–1351. [CrossRef] [PubMed]\n18. Luz, F.A.C.D.; Marinho, E.D.C.; Nascimento, C.P .; Marques, L.D.A.; Delfino, P .F.R.; Antonioli, R.M.; de Araujo, R.A.; Silva, M.J.B.\nThe effect of delayed treatment in breast cancer patients: How much is too late? An experience of a single-center study effect of\nsurgery delay in survival. Surg. Oncol. 2022 ,44, 101854. [CrossRef] [PubMed]\n19. Wiener, A.A.; Hanlon, B.M.; Schumacher, J.R.; Vande Walle, K.A.; Wilke, L.G.; Neuman, H.B. Reexamining time from breast\ncancer diagnosis to primary breast surgery. JAMA Surg. 2023 ,158, 485–492. [CrossRef] [PubMed]\n20. Bleicher, R.J.; Ruth, K.; Sigurdson, E.R.; Beck, J.R.; Ross, E.; Wong, Y.; Patel, S.; Boraas, M.; Chang, E.; Topham, N.; et al. Time to\nsurgery and breast cancer survival in the United States. JAMA Oncol. 2016 ,2, 330–339. Erratum in JAMA Oncol. 2016 ,2, 1244.\n[CrossRef] [PubMed]\n21. Bleicher, R.J.; Ruth, K.; Sigurdson, E.R.; Ross, E.; Wong, Y.; Patel, S.; Boraas, M.; Topham, N.; Egleston, B. Preoperative delays in\nthe US Medicare population with breast cancer. J. Clin. Oncol. 2012 ,30, 4485–4492. [CrossRef] [PubMed]\n22. Vaz, S.C.; Woll, J.P .P .; Cardoso, F.; Groheux, D.; Cook, G.; Ulaner, G.; Jacene, H.; Rubio, I.; Schoones, J.; Peeters, M.-J.; et al. Joint\nEANM-SNMMI guideline on the role of 2-[18F]FDG PET/CT in no special type breast cancer (endorsed by the ACR, ESSO,\nESTRO, EUSOBI/ESR, and EUSOMA). Eur. J. Nucl. Med. Mol. Imaging 2024 ,51, 2706–2732. [CrossRef] [PubMed]\nDisclaimer/Publisher’s Note: The statements, opinions and data contained in all publications are solely those of the individual\nauthor(s) and contributor(s) and not of MDPI and/or the editor(s). MDPI and/or the editor(s) disclaim responsibility for any injury to\npeople or property resulting from any ideas, methods, instructions or products referred to in the content.\nhttps://doi.org/10.3390/curroncol33040203"
  ],
  "text": "Received: 11 February 2026\nRevised: 25 March 2026\nAccepted: 31 March 2026\nPublished: 1 April 2026\nCopyright: © 2026 by the authors.\nLicensee MDPI, Basel, Switzerland.\nThis article is an open access article\ndistributed under the terms and\nconditions of the Creative Commons\nAttribution (CC BY) license.\nArticle\nThe Yield of Staging Investigations in Patients with Breast\nCancer Planned for Neoadjuvant Chemotherapy\nKadhim Taqi1,2,*\n, Camelia Ursu3, Susan Isherwood4, Rabia Raheel4, Julia Downey5, Jeffrey Q. Cao6,7,\nSasha Lupichuk8\n, Omar Khan8\n, Nancy Nixon8, May Lynn Quan1,5,7and Alison Laws1,7,*\n1Division of Surgical Oncology, Department of Surgery, University of Calgary, Calgary, AB T2N 1N4, Canada\n2Division of Surgical Oncology, Department of Surgery, Sultan Qaboos Comprehensive Cancer Care and\nResearch Center, University Medical City, Muscat 123, Oman\n3Cumming School of Medicine, University of Calgary, Calgary, AB T2N 1N4, Canada\n4Department of Surgery, University of Calgary, Calgary, AB T2N 1N4, Canada\n5Department of Community Health Sciences, University of Calgary, Calgary, AB T2N 1N4, Canada\n6Division of Radiation Oncology, Arthur J.E. Child Comprehensive Cancer Centre,\nCalgary, AB T2N 1N4, Canada\n7Department of Oncology, University of Calgary, Calgary, AB T2N 1N4, Canada\n8Division of Medical Oncology, Department of Oncology, University of Calgary, Calgary, AB T2N 1N4, Canada\n*Correspondence: kadhim.taqi@ucalgary.ca (K.T.); alison.laws@albertahealthservices.ca (A.L.)\nSimple Summary\nRadiological imaging is commonly used in patients with breast cancer to assess disease\nstage before starting chemotherapy, but its benefit varies by stage. Using population-\nwide data, we studied how often these tests detected cancer that had already spread in\npatients planned for chemotherapy before surgery. We found that cancer spread was very\nuncommon in patients with small tumors and no lymph node involvement, even when\nchemotherapy was planned, suggesting that routine staging scans can be safely avoided\nin this group. In contrast, patients with larger tumors or lymph node involvement had\na higher likelihood of cancer spread. These results support more selective use of staging\ntests, which could reduce unnecessary scans, costs, patient anxiety, and treatment delays,\nwhile helping refine future guidelines and policy decisions.\nAbstract\nBackground: Patients with breast cancer planned for neoadjuvant chemotherapy (NAC)\nrepresent a diverse population including high-risk early breast cancer (EBC) and locally\nadvanced breast cancer (LABC). Staging investigations are routinely performed, but the\nclinical utility is unclear. Methods: Using a provincial cancer registry, we identified\nbreast cancer patients referred for NAC between 2020 and 2022. Patients with staging\ninvestigations were stratified into EBC (anatomic clinical stage I–II) and LABC (stage III).\nRates of metastatic (M1) disease and associated factors were assessed. Results: Among\n529 EBC patients, 515 (97.4%) underwent staging. The M1 disease rate was 5.4%. The M1\nrate for cT1-2N0 was 1.1%, and for cT1-2N1 it was 7.9%. In multivariable analysis, cT1N1\n(OR 5.31; 95% CI 1.05–27.0; p= 0.044) and cT2N1 (OR 4.59; 95% CI 1.02–20.67; p= 0.047)\nwere associated with M1 disease in EBC. All 320 LABC patients underwent staging. The\nM1 disease rate was 22.8%, significantly higher than in EBC ( p< 0.001). A higher cT/N\nstage correlated with M1 disease in LABC, although most subgroups demonstrated rates\nof≥10%. Conclusions: These findings support a risk-adapted approach to pre-treatment\nstaging in patients planned for NAC, omitting staging in asymptomatic cT1–2N0 disease,\nconsidering it for node-positive EBC, and performing it routinely in LABC.\nCurr. Oncol. 2026 ,33, 203 https://doi.org/10.3390/curroncol33040203\n\nCurr. Oncol. 2026 ,33, 203 2 of 10\nKeywords: staging investigations; breast cancer; neoadjuvant chemotherapy; locally\nadvanced; systemic staging\n1. Introduction\nStaging investigations alter the management of patients newly diagnosed with breast\ncancer when distant metastatic disease is identified. In patients with locoregionally ad-\nvanced breast cancer (LABC), systemic staging is recommended due to the relatively high\nlikelihood of detecting distant metastases [ 1–3]. Conversely, the diagnostic yield of staging\nis much lower for early breast cancer (EBC), and thus its use is more debated, with current\nguidelines varying in their recommendations. The National Comprehensive Cancer Net-\nwork (NCCN), American Society of Clinical Oncology (ASCO) and Cancer Care Ontario\ndiscourage routine staging for asymptomatic patients with stage I or II disease [ 1,4,5]. In\ncontrast, the European Society for Medical Oncology (ESMO) supports the use of staging\nfor patients with node-positive disease, tumors larger than 5 cm (T3), or aggressive tumor\nbiology (3), while the American College of Radiology (ACR) recommends staging for\npatients with stage IIB or higher disease [6].\nPatients referred for neoadjuvant chemotherapy (NAC) represent a distinct subgroup\nencompassing both early and locally advanced disease. These patients often present with\nhigher-risk features that render them eligible for NAC such as node positivity or more\naggressive biologic subtypes (even when presenting with a lower anatomic clinical stage).\nThe diagnostic yield and clinical utility of staging investigations in this population is not\nwell-characterized. Multiple studies have shown high rates of staging in patients with EBC,\nespecially before NAC initiation [ 7–9]. Overuse of staging investigations is costly [ 7,10] and\nmay expose patients to harms such as unnecessary radiation, invasive follow-up procedures,\nand anxiety over false-positive findings [ 11]. Further, staging workups can delay the timely\ninitiation of therapy, potentially impacting treatment outcomes [ 12]. Nevertheless, accurate\nassessment of disease extent remains crucial for prognostication and to guide treatment\nstrategies, including avoidance of chemotherapy toxicity for some patients when metastatic\ndisease is confirmed.\nAcross the six tertiary and regional cancer centers in the province of Alberta, Canada,\ndistant staging investigations are performed routinely for patients with breast cancer\nplanned for NAC. The objective of this study was to evaluate the rate of de novo metastatic\n(M1) disease detected in staging investigations among patients referred for NAC, stratified\nby EBC and LABC, and to identify factors associated with M1 disease.\n2. Materials and Methods\nInstitutional review board approval was obtained from the Health Research Ethics\nBoard of Alberta–Cancer Committee (HREBA-CC), and a waiver of consent was granted\ngiven the minimal-risk nature of the study. All patients with breast cancer referred to\nmedical oncology for consideration of NAC between 2020 and 2022 were identified from the\nAlberta Cancer Registry, which captures all new cancers in the province of approximately\nfive million individuals. Patients who did not undergo any distant staging investigations\nwere excluded. Two cohorts were generated based on the clinical T/N stage (cT/cN) at\npresentation according to the American Joint Committee on Cancer (AJCC) 8th edition\nanatomic staging system. The EBC cohort was defined as stage I-II (cT1-2 N0-1 or cT3N0)\nand the LABC cohort as stage III (cT3N1, any cT4, and any cN2-3).\nThe primary outcome of interest was final metastatic status after staging (M0 vs. M1),\nobtained from the Alberta Cancer Registry and confirmed in the medical record. Details of\nhttps://doi.org/10.3390/curroncol33040203\n\nCurr. Oncol. 2026 ,33, 203 3 of 10\nthe staging workup were obtained from medical chart review. Each distant staging investi-\ngation was documented, including computed tomography (CT) of the chest and abdomen\nwith or without pelvis (CA ±P), bone scan, brain imaging (CT or Magnetic Resonant\nImaging (MRI)) and positron emission tomography (PET). Staging results according to the\nreporting radiologist’s interpretation were categorized as negative (any findings considered\nlikely benign), indeterminate (findings could not be confidently classified as benign or\nmalignant) or suspicious (findings were concerning for malignancy and considered likely\nmetastatic). Further workup was defined as additional imaging tests or biopsies prompted\nby findings on the baseline staging scans.\nRemaining demographic, disease and treatment characteristics were obtained from\nmedical chart review. Histological type, grade, estrogen receptor (ER), progesterone recep-\ntor (PR), and human epidermal growth factor receptor-2 (HER2) status were obtained from\nthe pre-treatment core biopsy. Hormone receptor positivity (HR+) and HER2 positivity\n(HER2+) were defined according to the American Society of Clinical Oncology and the\nCollege of American Pathologists (ASCO/CAP) guidelines [ 13] and were used to construct\nbiologic subtype categories of HR+/HER2 −, HER2+ and triple-negative (TN).\nStatistical Analysis\nThe EBC and LABC cohorts were analyzed separately. Descriptive statistics were used\nto summarize demographic and disease characteristics, with continuous variables reported\nas medians with interquartile ranges (IQRs) and categorical variables as frequencies and\nproportions. Time from pathologic diagnosis (biopsy date) to NAC initiation was compared\nby staging result using Mann–Whitney U tests. Associations between clinical factors (age,\ncT and cN, histologic type, grade, and biologic subtype) and M1 status were evaluated\nusing univariable logistic regression. Factors with statistically significant associations were\nincluded in multivariable logistic regression models. For the EBC cohort, the multivariable\nmodel included cT/N category, grade and biologic subtype (histologic type was excluded\ndue to a small sample size of lobular cancers). For the LABC cohort, samples sizes were\nsmall for individual cT/N categories. As such, two models were generated, one including\ncT and cN as separate variables and one using AJCC subgroups of stage III (A vs. B vs.\nC), along with age and grade. For both cohorts, we reported absolute rates of M1 disease\nfor pre-planned subgroups of cT/N category and biologic subtype, reflecting groups for\nwhich staging investigations have been recommended in some guidelines. All analyses\nwere performed using StataIC version 16.1 (StataCorp LLC, College Station, TX, USA). A\np-value of <0.05 was considered statistically significant.\n3. Results\n3.1. Early Breast Cancer Cohort (Stage IA-IIB)\nAmong 529 eligible patients with EBC, 14 patients had no staging investigations and\nwere excluded. The remaining 515 (97.4%) underwent CT CA +/ −P and/or bone scan\nand were included for analysis. Most patients ( n= 469, 91.1%) had guideline-concordant\nstaging with both CT CA ±P and bone scan. Additional brain imaging was performed\nfor 48 patients (9.3%) and an additional PET scan for 4 patients (0.8%). Detailed staging\nresults are shown in Figure 1. Overall, M1 disease was identified in 28/515 patients (5.4%;\n95% CI, 3.8–7.7%). Sites of distant metastases were as follows: lung ( n= 14, 50.0%), bone\n(n= 12, 42.9%), liver ( n= 11, 39.3%), brain ( n= 1, 3.6%), and other ( n= 9, 32.2%). Among\nM0 patients, those who required additional workup ( n= 114, 22.1%) after baseline staging\nscans experienced a median delay of five days to NAC initiation (43 vs. 38 days; p= 0.03).\nhttps://doi.org/10.3390/curroncol33040203\n\nCurr. Oncol. 2026 ,33, 203 4 of 10\nFigure 1. Results of staging investigations in patients with early and locoregionally advanced breast\ncancer referred for neoadjuvant chemotherapy.\nClinical characteristics stratified by M0 versus M1 disease are presented in Table 1.\nClinical T/N stage, histology, grade and biologic subtype were all significantly associated\nwith M1 status (all p< 0.05) in univariable analyses. In multivariable analysis, only the\ncT1N1 (OR 5.31; 95% CI 1.05–27.0; p= 0.044) and cT2N1 (OR 4.59; 95% CI 1.02–20.67;\np= 0.047 ) stage remained significantly associated with higher odds of M1 disease (Table 2).\nWhile not statistically significant, TN or HER2+ subtypes and grade 3 tumors showed\nlower odds of M1 disease. Rates of M1 disease in pre-specified subgroups of cT/N category\nand biologic subtype are presented in Table 3. Most notably, the M1 rate was 1.1% (2/174)\nfor cT1-2N0, 5.4% (2/37) for cT3N0 and 7.9% (24/302) for cT1-2N1.\nTable 1. Baseline characteristics for early breast cancer (stage I–II) patients with M0 vs. M1 disease.\nVariable M0 ( n= 487) M1 ( n= 28) p-Value\nMedian age in years (IQR) 50 (42–60) 53 (47–62) 0.17\ncT/N stage\n0.04T1N0 36 (7.4%) 0 (0%)\nT2N0 138 (28.3%) 2 (7.1%)\nT1N1 71 (14.6%) 7 (25.0%)\nT2N1 207 (42.5%) 17 (60.7%)\nT3N0 35 (7.2%) 2 (7.1%)\nHistology\n0.02 Ductal 473 (97.1%) 25 (89.3%)\nLobular 14 (2.9%) 3 (10.7%)\nGrade\n0.04 1–2 158 (32.4%) 15 (53.6%)\n3 326 (66.9%) 13 (46.4%)\nER Status\n0.002 Positive 238 (48.9%) 22 (78.6%)\nNegative 249 (51.1%) 6 (21.4%)\nPR Status\n0.015 Positive 153 (31.4%) 15 (53.6%)\nNegative 334 (68.6%) 13 (46.4%)\nhttps://doi.org/10.3390/curroncol33040203\n\nCurr. Oncol. 2026 ,33, 203 5 of 10\nTable 1. Cont.\nVariable M0 ( n= 487) M1 ( n= 28) p-Value\nHER2 Status\n0.33 Positive 184 (37.8%) 8 (28.6%)\nNegative 303 (62.2%) 20 (71.4%)\nBiologic subtype\n0.005HR+/HER2 − 126 (25.9%) 15 (53.6%)\nTN 177 (36.3%) 5 (17.9%)\nHER2+ 184 (37.8%) 8 (28.5%)\nIQR: interquartile range. cT: clinical tumor stage. cN: clinical nodal stage. HR: hormone receptor. TN: triple-\nnegative. HER2: human epidermal growth factor receptor-2.\nTable 2. Multivariable analysis evaluating factors associated with M1 status in the early breast cancer\n(stage I–II) cohort.\nVariableUnadjusted\nOdds RatioAdjusted\nOdds RatioAdjusted 95%\nConfidence\nIntervalAdjusted\np-Value\ncT/N stage\nT1N0 No events No events - -\nT2N0 Reference Reference\nT3N0 3.94 2.35 0.30–18.28 0.414\nT1N1 6.80 5.31 1.05–26.99 0.044\nT2N1 5.67 4.59 1.02–20.67 0.047\nGrade\n1–2 Reference Reference\n3 0.40 0.48 0.22–1.08 0.076\nBiologic subtype\nHR+/HER2 − Reference Reference\nTN 0.24 0.43 0.14–1.27 0.125\nHER2+ 0.37 0.50 0.20–1.24 0.134\ncT stage: clinical tumor stage. cN stage: clinical nodal stage. HR: hormone receptor. TN: triple-negative. HER2:\nhuman epidermal growth factor receptor-2.\nTable 3. Absolute rates of M1 disease by cT/N stage and biologic subtype.\nOverall AJCC Stage cT/N All Biologic Subtypes HR+/HER2 − TN HER2+\nIA T1N0 0/36 (0%) -- -- --\nIIAT2N0 2/138 (1.4%) 0/17 (0%) 0/69 (0%) 2/52 (3.7%)\nT1N1 7/78 (9.0%) 5/28 (17.9%) 1/25 (4.0%) 1/25 (4.0%)\nIIBT3N0 2/37 (5.4%) 2/19 (10.5%) 0/12 (0%) 0/6 (0%)\nT2N1 17/224 (7.6%) 8/75 (10.7%) 4/60 (6.7%) 5/89 (5.6%)\nIIIAT1-2N2 2/43 (4.7%) 1/17 (5.9%) 0/10 (0%) 1/16 (6.3%)\nT3N1 9/77 (11.7%) 5/36 (13.9%) 1/13 (7.7%) 3/28 (10.7%)\nT3N2 1/10 (10.0%) * * *\nIIIBT4N0 4/17 (23.5%) * * *\nT4N1 23/80 (28.8%) 13/42 (31.0%) 1/12 (8.3%) 9/26 (34.6%)\nT4N2 7/19 (36.8%) * * *\nIIICT1-2N3 9/24 (37.5%) 4/13 (30.8%) 1/4 (25.0%) 4/7 (57.1%)\nT3N3 4/16 (25.0%) * * *\nT4N3 14/33 (42.4%) 3/7 (42.9%) 7/12 (58.3%) 4/14 (28.6%)\ncT stage: clinical tumor stage. cN stage: clinical nodal stage. HR: hormone receptor. TN: triple-negative.\nHER2: human epidermal growth factor receptor-2. * Omitted due to small sample size (<20 patients in total).\nhttps://doi.org/10.3390/curroncol33040203\n\nCurr. Oncol. 2026 ,33, 203 6 of 10\n3.2. Locally Advanced Breast Cancer Cohort (Stage III)\nAmong 320 eligible patients with LABC, all (100%) underwent CT CA +/ −P and/or\nbone scan and were included for analysis. Most patients ( n= 293; 91.5%) received guideline-\nconcordant staging with both CT CA ±P and a bone scan. Additional brain imaging was\nperformed in 40 patients (12.5%) and an additional PET scan in 7 patients (2.2%). Detailed\nstaging results are shown in Figure 1. Overall, M1 disease was identified in 73/320 patients\n(22.8%; 95% CI, 18.6–27.7%), a significantly higher rate than the EBC cohort ( p< 0.001).\nSites of distant metastases were as follows: bone ( n= 41, 56.2%), lung ( n= 39, 53.4%), liver\n(n= 29, 39.7%), brain ( n= 3, 4.1%) and other ( n= 25, 34.2%). Among M0 patients, those\nwho required additional workup after baseline staging scans did not experience any delay\nto NAC initiation (median 36 days for both, p= 0.54).\nClinical characteristics stratified by M0 versus M1 disease are shown in Table 4. Age,\ncT and cN categories as well as overall AJCC stage, and grade were significantly associated\nwith M1 disease (all p< 0.05) in univariable analyses. In multivariable analysis, cT4 and\ncN3 disease remained significantly associated with higher odds of M1 disease, whereas\nstage IIIA disease (vs. IIIB or IIIC) and grade 3 were associated with significantly lower\nodds of M1 (all p< 0.05, Supplementary Tables S1 and S2). Notably, all cT, cN, and grade\nsubgroups for the LABC cohort had absolute M1 rates ≥10%. The absolute rate of M1\ndisease for stage IIIA was 9.2% (12/130); rates for each T/N category are shown in Table 3.\nTable 4. Baseline characteristics for locally advanced patients (stage III) with M0 vs. M1 disease.\nVariable M0 ( n= 247) M1 ( n= 73) p-Value\nMedian age in years (IQR) 49 (41–62) 57 (44–67) 0.01\ncT\n<0.0011–2 57 (23.0%) 11 (15.0%)\n3 89 (36.0%) 14 (19.2%)\n4a-c 39 (15.8%) 30 (41.1%)\n4d 62 (25.1%) 18 (25.7%)\ncN\n0.0090 13 (5.3%) 4 (5.5%)\n1 125 (50.6%) 32 (43.8%)\n2 62 (25.1%) 10 (13.7%)\n3 47 (19.0%) 27 (37.0%)\nStage\n<0.001IIIA (T3N1 and T0-3 N2) 118 (47.8%) 12 (16.4%)\nIIIB (T4 N0-2) 82 (33.2%) 34 (46.6%)\nIIIC (T any N3) 47 (19.0%) 27 (37.0%)\nHistology\n0.74 Ductal 240 (97.2%) 72 (98.6%)\nLobular 6 (2.4%) 1 (1.4%)\nGrade\n0.003 1–2 68 (27.5%) 34 (46.6%)\n3 179 (72.5%) 39 (53.4%)\nER Status\n0.23 Positive 150 (60.7%) 50 (68.5%)\nNegative 97 (39.3%) 23 (31.5%)\nPR Status\n0.33 Positive 106 (42.9%) 36 (49.3%)\nNegative 141 (57.1%) 37 (50.7%)\nHER2 Status\n0.91 Positive 83 (33.6%) 24 (32.9%)\nNegative 164 (66.4%) 49 (67.1%)\nhttps://doi.org/10.3390/curroncol33040203\n\nCurr. Oncol. 2026 ,33, 203 7 of 10\nTable 4. Cont.\nVariable M0 ( n= 247) M1 ( n= 73) p-Value\nBiologic subtype\n0.76HR+/HER2 − 108 (43.7%) 35 (48.0%)\nTN 56 (22.7%) 14 (19.2%)\nHER2+ 83 (33.6%) 24 (32.9%)\nIQR: interquartile range. cT: clinical tumor stage. cN: clinical nodal stage. HR: hormone receptor. TN: triple-\nnegative. HER2: human epidermal growth factor receptor-2.\n4. Discussion\nThis study uniquely uses a large population-based cohort of breast cancer patients\nreferred for NAC with unselected use of staging investigations, allowing for an accurate\nand generalizable assessment of the diagnostic yield of staging in this population. We found\na low rate of M1 disease among patients with cT1–T2N0 disease (1% overall), supporting\nthe omission of routine staging in this population even when NAC is planned, which is\nconsistent with current guidelines for all-comers with early breast cancer [ 3–5]. In contrast,\nthe incidence of M1 disease was higher for EBC patients with cT3N0 (5%) and N1 (8–9%)\ndisease, suggesting that staging may be justified in these subgroups. Notably, a trend\ntoward higher M1 rates was also observed among patients with ER+/HER2 −subtype\nand grade 1–2 tumors. While these did not reach statistical significance in multivariable\nanalysis, the low event rate may have limited power. Nonetheless, our findings do not\nclearly support preferential use of staging in aggressive subtypes (e.g., TN and HER2+)\neven at a lower clinical stage of disease, as some guidelines have suggested, though this\nobservation should be interpreted with caution. In contrast, patients with LABC exhibited\na significantly higher burden of metastatic disease, with even the lowest-risk subgroups\ndemonstrating M1 rates of ≥9–10%, reinforcing guideline recommendations for routine\nstaging in this population.\nMost studies evaluating the diagnostic yield of staging investigations in breast can-\ncer included all-comers and were stratified by stage. In such studies, the overall rate\nof M1 disease is low (0–6%) for EBC populations [ 11,13,14] but significant for LABC\n(18–36%) [8,10,15–17] . The likelihood of M1 disease has also been generally consistent\nacross tumor subtypes [ 13,14]. Cohorts of high-risk subgroups such as patients referred\nfor NAC are more limited. A retrospective review from Memorial Sloan Kettering Cancer\nCentre [ 7] included 303 NAC patients with stage I-II disease, of whom 85% had staging\ninvestigations, mostly with PET/CT. The M1 rate detected by staging was 4.9%, almost\nall (n= 14/15) in patients with cN1 disease. They concluded that pre-NAC staging is not\nnecessary for patients with EBC. A study from the United Kingdom evaluated 163 patients\nreferred for NAC where staging was routine. The overall rate of M1 disease was 9.3%,\nbut in the cohort with T1-3N0, the rate was only 1.6% [ 9]. Our findings are aligned with\nthese prior studies, but our larger sample size allowed for further stratification by stage\nand biologic subtype to develop recommendations more tailored to individual tumor\ncharacteristics.\nIn our cohort, staging investigations resulted in small delays to treatment (median\n5 days) for patients who required additional workup after baseline scans. While time-to-\ntreatment benchmarks are lacking for NAC patients specifically, delays of ≥4–8 weeks\nfrom breast cancer diagnosis to treatment are associated with worse outcomes in those\nundergoing surgery first [ 18–20]. As such, the differences in time to treatment observed in\nour study are likely clinically insignificant. Other studies have found delays of 6–14 days for\npatients who undergo staging [ 21], so this issue warrants consideration in the local context.\nhttps://doi.org/10.3390/curroncol33040203\n\nCurr. Oncol. 2026 ,33, 203 8 of 10\nSeveral limitations of this study should be acknowledged. Despite the large overall\nsample of 835 patients, stratification by clinical T/N stage and biologic subtype resulted\nin small subgroup sizes, limiting the precision of some estimates. Similarly, multivariable\nanalyses—particularly in the EBC cohort—may have been underpowered given the rel-\natively low event rate. Given the retrospective nature of this study, there is a possibility\nof selection bias in staging use and potential for heterogeneity in the type of modality\nchosen, both of which could influence diagnostic yield. However, exclusions due to non-\nperformance of staging were very minimal ( n= 14 patients, 1.6%) and type of staging\nwas quite homogenous, with 91% of patients in both EBC and LABC cohorts undergoing\nguideline-concordant CT CA +/ −P and bone scan. Collectively, this supports the minimal\nrisk of these issues. PET scan was infrequently used in this population, limiting the gener-\nalizability of our findings to centers where this modality is routinely incorporated. PET has\nbeen shown to increase the detection of M1 disease and is being increasingly incorporated\ninto clinical practice guidelines, primarily for LABC [ 1,4,22]. In addition, clinical staging\nwas used for group classification, which may be subject to misclassification, particularly\nwith respect to nodal assessment. However, this reflects the reality of available information\nbefore NAC is initiated. Finally, with any retrospective medical chart review, there is a\nrisk of variable misclassification, though variables included in this study were generally\nclearly documented.\n5. Conclusions\nBased on our findings, we advocate for the omission of routine staging investigations\nfor asymptomatic patients with cT1-2N0 disease planned for NAC, in keeping with current\nguideline recommendations. EBC patients with cT3N0 or N1 disease may be considered\nfor staging, and staging should be routine for those with LABC. Staging guidelines in our\nprovince are currently under review and will be informed by this study, and our results are\nwidely generalizable to other jurisdictions.\nSupplementary Materials: The following supporting information can be downloaded at:\nhttps://www.mdpi.com/article/10.3390/curroncol33040203/s1, Table S1: Multivariable analysis #1\nevaluating factors associated with M1 status in the locally advanced (stage III) cohort, including age,\ncT, cN and grade; Table S2: Multivariable analysis #2 evaluating factors associated with M1 status in\nthe locally advanced (stage III) cohort, including age, overall AJCC stage and grade.\nAuthor Contributions: Conceptualization, K.T., A.L. and M.L.Q.; methodology, S.I. and A.L.; valida-\ntion, K.T., M.L.Q. and A.L.; formal analysis, A.L.; investigation, K.T. and C.U.; resources, S.I.; data\ncuration, C.U., R.R. and J.D.; writing—original draft preparation, K.T.; writing—review and editing,\nJ.Q.C., S.L., O.K., N.N., M.L.Q. and A.L.; visualization, A.L.; supervision, A.L.; project administration,\nS.I. All authors have read and agreed to the published version of the manuscript.\nFunding: This research received no external funding.\nInstitutional Review Board Statement: The study was conducted in accordance with the Declaration\nof Helsinki and approved by the Institutional Review Board of the Health Research Ethics Board of\nAlberta (HREBA)–Cancer Committee (CC). (Approval code: HREBA.CC-24-0235; Approval Date: 8\nAugust 2024).\nInformed Consent Statement: Patient consent was waived by the ethical board (Health Research\nEthics Board of Alberta–Cancer Committee) given the minimal-risk nature of the study.\nData Availability Statement: The datasets generated during and/or analyzed during the current\nstudy are not publicly available due to patient privacy but are available from the corresponding\nauthor on reasonable request.\nConflicts of Interest: The authors declare no conflicts of interest.\nhttps://doi.org/10.3390/curroncol33040203\n\nCurr. Oncol. 2026 ,33, 203 9 of 10\nAbbreviations\nThe following abbreviations are used in this manuscript:\nLABC Locally advanced breast cancer\nEBC Early breast cancer\nNCCN National Comprehensive Cancer Network\nASCO American Society of Clinical Oncology\nESMO European Society of Medical Oncology\nACR American College of Radiology\nNAC Neoadjuvant chemotherapy\nM1 De novo metastatic\nAJCC American Joint Committee on Cancer\nCT Computed tomography\nMRI Magnetic resonant imaging\nPET Positron emission tomography\nCA±P Chest and abdomen with or without pelvis\nER Estrogen receptor\nPR Progesterone receptor\nHER2 Epidermal growth factor receptor-2\nHR+ Hormone receptor positivity\nHER2+ HER2 receptor positivity\nCAP College of American Pathologists\nIQRs Interquartile ranges\nTN Triple-negative\nOR Odds ratio\nReferences\n1. Gradishar, W.; Moran, M.; Abraham, J.; Abramson, V .; Aft, R.; Agnese, D.; Allison, K.; Anderson, B.; Bailey,\nJ.; Burstein, H.; et al. National Comprehensive Cancer Network. In NCCN Clinical Practice Guidelines in Oncol-\nogy: Breast Cancer ; National Comprehensive Cancer Network: Fort Washington, PA, USA, 2025. Available online:\nhttps://www.nccn.org/professionals/physician_gls/pdf/breast.pdf (accessed on 20 October 2025).\n2. American Society of Clinical Oncology; American Board of Internal Medicine. Choosing Wisely: Cancer Tests and Treatments.\nPublished 2012. Available online: http://www.choosingwisely.org/patient-resources/cancer-tests-and-treatments (accessed on\n20 October 2025).\n3. Loibl, S.; André, F.; Bachelot, T.; Barrios, C.; Burstein, H.; Cadoso, M.; Carey, L.; Dawood, S.; Del Mastro, L.; Denkert, C.; et al.\nEarly breast cancer: ESMO Clinical Practice Guideline for diagnosis, treatment and follow-up. Ann. Oncol. 2024 ,35, 159–182.\n[CrossRef] [PubMed]\n4. Arnaout, A.; Varela, N.P .; Allarakhia, M.; Grimard, L.; Hey, A.; Lau, J.; Thain, L.; Eisen, A. Baseline staging imaging for distant\nmetastasis in women with stage I, II, and III breast cancer. Curr. Oncol. 2020 ,27, e123–e145. [CrossRef] [PubMed]\n5. American Society of Clinical Oncology. Choosing Wisely. ASCO. Available online: https://www.asco.org/news-\ninitiatives/current-initiatives/cancer-care-initiatives/value-cancer-care/choosing-wisely (accessed on 2 November 2025).\n6. Expert Panel on Breast Imaging; McDonald, E.S.; Scheel, J.R.; Lewin, A.A.; Weinstein, S.; Dodelzon, K.; Dogan, B.; Fitzpatrick, A.;\nKuzmiak, C.; Newell, M.; et al. ACR Appropriateness Criteria®Imaging of Invasive Breast Cancer. J. Am. Coll. Radiol. 2024 ,21,\nS168–S202. [CrossRef] [PubMed]\n7. Srour, M.K.; Lee, M.; Walcott-Sapp, S.; Luu, M.; Chung, A.; Giuliano, A.; Amersi, F. Overuse of preoperative staging of patients\nundergoing neoadjuvant chemotherapy for breast cancer. Ann. Surg. Oncol. 2019 ,26, 3289–3294. [CrossRef] [PubMed]\n8. Roszkowski, N.; Lam, S.S.; Copson, E.; Cutress, R.I.; Oeppen, R. Expanded criteria for pretreatment staging CT in breast cancer.\nBJS Open 2021 ,5, zraa006. [CrossRef] [PubMed]\n9. Broadbent, R.; Ralston, S.; Lauder, J.; Howell, S. Outcome of CT staging prior to neoadjuvant chemotherapy in patients with early\nbreast cancer. Breast J. 2020 ,26, 2415–2419. [CrossRef] [PubMed]\n10. Srour, M.K.; Lee, M.; Walcott-Sapp, S.; Luu, M.; Chung, A.; Giuliano, A.; Amersi, F. Incidental radiologic findings in breast cancer\npatients who undergo staging prior to neoadjuvant chemotherapy. Breast J. 2021 ,27, 345–351. [CrossRef]\n11. Kamel, D.; Youssef, V .; Hopman, W.M.; Mates, M. Staging investigations in asymptomatic early breast cancer patients at the\nCancer Centre of Southeastern Ontario. Curr. Oncol. 2021 ,28, 2190–2198. [CrossRef]\nhttps://doi.org/10.3390/curroncol33040203\n\nCurr. Oncol. 2026 ,33, 203 10 of 10\n12. Lohrisch, C.; Paltiel, C.; Gelmon, K.; Speers, C.; Taylor, S.; Barnett, J.; Olivotto, I. Impact on survival of time from definitive surgery\nto initiation of adjuvant chemotherapy for early-stage breast cancer. J. Clin. Oncol. 2006 ,24, 4888–4894. [CrossRef] [PubMed]\n13. Allison, K.H.; Hammond, M.E.H.; Dowsett, M.; McKernin, S.; Carey, L.; Fitzgibbons, P .; Hayes, D.; Lakhani, S.; Chavez-MacGregor,\nM.; Perlmutter, J.; et al. Estrogen and progesterone receptor testing in breast cancer: ASCO/CAP guideline update. J. Clin. Oncol.\n2020 ,38, 1346–1366. [CrossRef] [PubMed]\n14. Bychkovsky, B.L.; Guo, H.; Sutton, J.; Spring, L.; Faig, J.; Dagogo-Jack, I.; Battelli, C.; Houlihan, M.J.; Yeh, T.C.; Come, S.E.; et al.\nUse and Yield of Baseline Imaging and Laboratory Testing in Stage II Breast Cancer. Oncologist 2016 ,21, 1495–1501. [CrossRef]\n[PubMed]\n15. Barrett, T.; Bowden, D.J.; Greenberg, D.C.; Brown, C.; Wishart, G.; Britton, P . Radiological staging in breast cancer: Which\nasymptomatic patients to image and how. Br. J. Cancer 2009 ,101, 1522–1528. [CrossRef] [PubMed]\n16. Alkazaz, A.A.; Ali, N.F.; Salman, A.Z.; Almahari, S.; Altaei, T.; Albati, W.; Habib, H.; Alsadoon, A.; Almawlani, N.; Alkhabbaz, F.;\net al. Need for staging investigations in newly diagnosed breast cancer: Establishing local guidelines for radiological staging in\nBahrain. Eur. J. Breast Health 2024 ,20, 136–140. [CrossRef] [PubMed]\n17. Ali, B.; Mubarik, F.; Zahid, N.; Sattar, A.K. Clinicopathologic features predictive of distant metastasis in patients diagnosed with\ninvasive breast cancer. JCO Glob. Oncol. 2020 ,6, 1346–1351. [CrossRef] [PubMed]\n18. Luz, F.A.C.D.; Marinho, E.D.C.; Nascimento, C.P .; Marques, L.D.A.; Delfino, P .F.R.; Antonioli, R.M.; de Araujo, R.A.; Silva, M.J.B.\nThe effect of delayed treatment in breast cancer patients: How much is too late? An experience of a single-center study effect of\nsurgery delay in survival. Surg. Oncol. 2022 ,44, 101854. [CrossRef] [PubMed]\n19. Wiener, A.A.; Hanlon, B.M.; Schumacher, J.R.; Vande Walle, K.A.; Wilke, L.G.; Neuman, H.B. Reexamining time from breast\ncancer diagnosis to primary breast surgery. JAMA Surg. 2023 ,158, 485–492. [CrossRef] [PubMed]\n20. Bleicher, R.J.; Ruth, K.; Sigurdson, E.R.; Beck, J.R.; Ross, E.; Wong, Y.; Patel, S.; Boraas, M.; Chang, E.; Topham, N.; et al. Time to\nsurgery and breast cancer survival in the United States. JAMA Oncol. 2016 ,2, 330–339. Erratum in JAMA Oncol. 2016 ,2, 1244.\n[CrossRef] [PubMed]\n21. Bleicher, R.J.; Ruth, K.; Sigurdson, E.R.; Ross, E.; Wong, Y.; Patel, S.; Boraas, M.; Topham, N.; Egleston, B. Preoperative delays in\nthe US Medicare population with breast cancer. J. Clin. Oncol. 2012 ,30, 4485–4492. [CrossRef] [PubMed]\n22. Vaz, S.C.; Woll, J.P .P .; Cardoso, F.; Groheux, D.; Cook, G.; Ulaner, G.; Jacene, H.; Rubio, I.; Schoones, J.; Peeters, M.-J.; et al. Joint\nEANM-SNMMI guideline on the role of 2-[18F]FDG PET/CT in no special type breast cancer (endorsed by the ACR, ESSO,\nESTRO, EUSOBI/ESR, and EUSOMA). Eur. J. Nucl. Med. Mol. Imaging 2024 ,51, 2706–2732. [CrossRef] [PubMed]\nDisclaimer/Publisher’s Note: The statements, opinions and data contained in all publications are solely those of the individual\nauthor(s) and contributor(s) and not of MDPI and/or the editor(s). MDPI and/or the editor(s) disclaim responsibility for any injury to\npeople or property resulting from any ideas, methods, instructions or products referred to in the content.\nhttps://doi.org/10.3390/curroncol33040203",
  "extracted_at": "2026-06-14T05:11:21.783888Z"
}